cookyjar/__init__.py
cookyjar/frontend/build/app.css
cookyjar/frontend/build/asset-manifest.json
cookyjar/frontend/build/index.html
cookyjar/frontend/build/static/js/main.f90f668e.js
cookyjar/frontend/build/static/js/main.f90f668e.js.LICENSE.txt
cookyjar/frontend/build/static/js/main.f90f668e.js.map
cookyjar-0.0.6.dist-info/LICENSE
cookyjar-0.0.6.dist-info/METADATA
cookyjar-0.0.6.dist-info/WHEEL
cookyjar-0.0.6.dist-info/top_level.txt
cookyjar-0.0.6.dist-info/RECORD
